luxai2022/__init__.py
luxai2022/actions.py
luxai2022/config.py
luxai2022/env.py
luxai2022/factory.py
luxai2022/globals.py
luxai2022/team.py
luxai2022/unit.py
luxai2022/map/__init__.py
luxai2022/map/bfs_deltas_gen.py
luxai2022/map/board.py
luxai2022/map/position.py
luxai2022/map/weather.py
luxai2022/map_generator/__init__.py
luxai2022/map_generator/generator.py
luxai2022/map_generator/symnoise.py
luxai2022/map_generator/timing.py
luxai2022/map_generator/visualize.py
luxai2022/map_generator/visualize_samples.py
luxai2022/pyvisual/__init__.py
luxai2022/pyvisual/visualizer.py
luxai2022/replay/__init__.py
luxai2022/replay/replay.py
luxai2022/spaces/__init__.py
luxai2022/spaces/act_space.py
luxai2022/spaces/obs_space.py
luxai2022/state/__init__.py
luxai2022/state/state.py
luxai2022/tools/__init__.py
luxai2022/tools/replay.py
luxai2022/utils/__init__.py
luxai2022/utils/animate.py
luxai2022/utils/utils.py
luxai_runner/__init__.py
luxai_runner/bot.py
luxai_runner/cli.py
luxai_runner/episode.py
luxai_runner/ext_to_command.py
luxai_runner/logger.py
luxai_runner/process.py
luxai_runner/utils.py
luxai_runner/tournament/__init__.py
luxai_runner/tournament/config.py
luxai_runner/tournament/matchmaking.py
luxai_runner/tournament/rankingsystem.py
luxai_runner/tournament/tournament.py
luxai2022-1.1.6.dist-info/METADATA
luxai2022-1.1.6.dist-info/WHEEL
luxai2022-1.1.6.dist-info/entry_points.txt
luxai2022-1.1.6.dist-info/top_level.txt
luxai2022-1.1.6.dist-info/RECORD
