Metadata-Version: 2.1
Name: luxai2022
Version: 1.1.6
Summary: The Lux AI Challenge Season 2
Home-page: https://github.com/Lux-AI-Challenge/Lux-Design-2022
Author: Lux AI Challenge
License: MIT
Keywords: reinforcement-learning machine-learning ai
Requires-Dist: numpy
Requires-Dist: pygame
Requires-Dist: termcolor
Requires-Dist: matplotlib
Requires-Dist: pettingzoo
Requires-Dist: vec-noise
Requires-Dist: omegaconf
Requires-Dist: gym (==0.19)
Requires-Dist: scipy
